{

    "nodatafound": "Nic jsem nenašel, máš smůlu.",
    "retrievingdata": "Měl bych pracovat, ale nechce se mi.",
    "datarestored": "Někdo mi ty informace dodal, takže máš štěstí.",
    "greyuser": "Jenom ti co se povyšují můžou sepnout bota.",
    "bouncer": "Když se ke mně takhle chováš, tak nečekej, že budu makat.",
    "online": "/me Línej bot verze.nemakám zapnut!",


    "welcome": "/me Ty vole nazdáár @%%NAME%%",
    "welcomeback": "/me Ty už si tu zase @%%NAME%% ? -.-",
    "songknown": "/me @%%NAME%%, tuhle songu ti někdo ukradl, takže máš smolíka.",
    "timelimit": "/me @%%NAME%%, Takže pouštět písničky delší než %%MAXLENGTH%% se ti zachtělo jo ? Smůlu máš kamaráde..",
    "permissionownsong": "/me :up: @%%NAME%% si myslí, že je něco víc tak ho při tom nechte!",
    "isblacklisted": "/me Jóó, zakázaný ovoce chutná vždy nejlíp, ale tady se jede tvrdý režim!",


    "isopen": "/me Zdá se malá aktivita, tak si hodíme ruletku. Jestli chceš risknout posun zpátky dej !join.",
    "winnerpicked": "/me A tady máme toho šťastnýho parchanta... @%%NAME%% je přesunut/a na pozici %%POSITION%%..",


    "alreadyadding": "/me Hráč tu už je slepče... změna pozice na pozici %%POSITION%%.",
    "adding": "/me Vnutil/a @%%NAME%% do fronty. Aktuální pozice: %%POSITION%%.",


    "usernotfound": "/me Uplavala.",
    "notdisconnected": "/me @%%NAME%% Jakože mohl bych tě hodit zpátky, ale víš jak to chodí. Lidi nepracujou, nikdo nic nedostane.",
    "noposition": "/me Hele sorry, po tej včerejší chlastačce mám výpadky paměti. Když mi něco připomenete, tak se MOŽNÁ rozvzpomenu.",
    "toolongago": "/me @%%NAME%% Já myslel, že už nepřijdeš a tak jsem tě za tu dobu %%TIME%% vymazal z mojí syntetické paměti.",
    "valid": "/me @%%NAME%% dezertoval/a před %%TIME%% a jelikož je můj programátor ujo tak bude přesunut na: %%POSITION%%.",


    "warning1": "/me @%%NAME%%, hej skřcku nejsi tady %%TIME%%, jestli se neozveš do 2 minut tak zažiješ peklo!",
    "warning2": "/me @%%NAME%%, jo tak ty se nebavíš. Uvidíme kdo se bude vztekat.",
    "afkremove": "/me @%%NAME%%, jelikož jsi trucoval/a %%TIME%% a mě to nebavilo, vyhodil jsem tě.. Byl/a jsi na pozici %%POSITION%%. Ozvi se aspoň jednou za %%MAXIMUMAFK%% minut jinak budu mít oprávnění buzerovat pořád.",    "caps": "/me @%%NAME%%, nepoužívej prosím capslock ani shift.",


    "askskip": "/me @%%NAME%%, drž hubu nebo vypadni jinam.",
    "spam": "/me @%%NAME%%, to že budeš spamovat ti nepomůže, jenom ze sebe uděláš větší hovado než jsi.",
    "roomadvertising": "/me @%%NAME%%, aléé... takhle chceš získat lidi ? Vždyť i politici maj větší charisma a lepší nápad.",
    "adfly": "/me @%%NAME%%, Jelikož nesnášíme změny tak ti nařizujeme, abys použil stejnej autowoot jak my:  http://origem-woot.com/",


    "invalidtime": "/me [@%%NAME%%] To cos zadal je pěkna hovadina kámo.",
    "nouserspecified": "/me [@%%NAME%%] Tak na tohohle borce si fakt nevzpomínám, sorrka.",
    "invaliduserspecified": "/me [@%%NAME%%] Jakože možná, ale fakt si nejsem jistej. Zeptej se někoho jiného.",
    "nolistspecified": "/me [@%%NAME%%] Ten seznam hledat nebudu, prostě ne!",
    "invalidlistspecified": "/me [@%%NAME%%] Který nevzdělaný prase psalo tenhle seznam ?",
    "novaliduserspecified": "/me [@%%NAME%%] Žádnej poctivej pracant nenalezen.",
    "nolimitspecified": "/me [@%%NAME%%] Žádnej limit nenalezen. Limity jsou totiž pro lamy.",
    "invalidlimitspecified": "/me [@%%NAME%%] Grr... když neumíš psát tak to nedělej.",
    "invalidpositionspecified": "/me [@%%NAME%%] Jakože je super, že chceš tohle. Já chci třeba lidi s mozkem, to by byla krása.",
    "toggleon": "/me [@%%NAME%%] %%FUNCTION%% aktivován.",
    "toggleoff": "/me [@%%NAME%%] %%FUNCTION%% deaktivován.",
    "afkremoval": "AFK removal",
    "afksremoved": "AFK's removed",
    "afklimit": "AFK limit",
    "autodisable": "autodisable",
    "autoskip": "autoskip",
    "newblacklisted": "/me [@%%NAME%%] Tato hovadina patří na blacklist ke svým druhům. [ %%AUTHOR%% - %%TITLE%% - %%MID%% ]",
    "blinfo": "[@%%NAME%%] Blacklist Info - Autor: %%AUTHOR%%, Název: %%TITLE%%, ID: %%SONGID%%",
    "blacklist": "blacklist",
    "cycleguard": "cycleguard",
    "timeguard": "timeguard",
    "chatfilter": "chatfilter",
    "historyskip": "historyskip",
    "lockdown": "lockdown",
    "lockguard": "lockguard",
    "usercommands": "usercommands",
    "motd": "MotD",
    "welcomemsg": "welcome message",
    "songstats": "song statistics",
    "etarestriction": "eta restriction",
    "voteskip": "voteskip",
    "voteskiplimit": "/me [@%%NAME%%] chceme trollit tak jsme nastavili limit na %%LIMIT%% mehů.",
    "voteskipexceededlimit": "/me @%%NAME%%, takový kraviny nikdo nechce poslouchat, sorrka vše má svůj limit. (%%LIMIT%% mehů).",
    "voteskipinvalidlimit": "/me [@%%NAME%%] Jakožes napsal kravinu, ale nechtěl bys po mě i duhu a jednorožce?",
    "voteskipsetlimit": "/me [@%%NAME%%] změna je život a tak je limit pro přeskočení nastaven na: %%LIMIT%%.",
    "activeusersintime": "/me [@%%NAME%%] všiml jsem si %%AMOUNT%% hráčů, kteří se bavili o nějakých hovadinách za posledních %%TIME%% minut.",
    "maximumafktimeset": "/me [@%%NAME%%] Maximální AFK čas nastaven na %%TIME%% minut.",
    "afkstatusreset": "/me [@%%NAME%%] Obnovil/a AFK limit hráči @%%USERNAME%%.",
    "inactivefor": "/me [@%%NAME%%] @%%USERNAME%% tady oxiduje svojí přítomností už %%TIME%%.",
    "autowoot": "/me Autowoot: http://origem-woot.com/",
    "brandambassador": "/me Brand Ambassador by měl slouži jako hlas hráčů plug.dj. Ve skutečnosti dělají to co se jim zachce, serou na komunity, dělaj si reklamu. Jestli chceš o těhlech divnolidech vědět víc, napiš někomu ze staffu.",
    "bouncerplusrank": "/me [@%%NAME%%] Musíš bejt manažér, abys mohl/a aktivovat Bouncer+.",
    "chatcleared": "/me [@%%NAME%%] Chce něco utajit a tak vymazal/a chat. Dostaňte to z něj/ní.",
    "deletechat": "/me [@%%NAME%%] Nemá rád hráče %%USERNAME%% a tak od něj smazal všechny zprávy.",
    "commandslink": "/me %%BOTNAME%% příkazy: %%LINK%%",
    "eatcookie": "/me Možeš někomu dát cukrovku v kolečku(sušenku). Stačí napsat !cookie @user.",
    "nousercookie": "/em Hráče %%NAME%% nevidím v místnosti. Nemůžeš se s ním přežírat. Stejně bys pak brečel/a, že jsi tlustej/á.",
    "selfcookie": "/me @%%NAME%%, Hej ty sobče, nabídni taky někomu!",
    "cookie": "/me @%%NAMETO%%, @%%NAMEFROM%% %%COOKIE%%",
    "cycleguardtime": "/me [@%%NAME%%] Cycleguard je nastaven na %%TIME%% minut.",
    "dclookuprank": "/me [@%%NAME%%] Pouze vyhazovači a výše mohou používat !dc a tak dělat matku ostatním hráčům.",
    "emojilist": "/me Seznam otravnejch smajlů: %%LINK%%",
    "notinwaitlist": "/me @%%NAME%%, nejsi ve frontě a tak nemáš na nic právo.",
    "eta": "/me @%%NAME%% pokud nebudeš vyhozen nebo zabanován(což by bylo super), tak si zahaješ za %%TIME%%.",
    "facebook": "/me Pokud nás chceš stalkovat i jinde, tak jdi tu: %%LINK%%",
    "starterhelp": "/me Jestli jseš vážně tak neschopnej a potřebuješ pomoct tak jdi sem: %%LINK%%",
    "roulettejoin": "/me @%%NAME%%  ty ses připojil do rulety ?! Neriskuj, napiš !leave a zachraň se.!",
    "jointime": "/me [@%%NAMEFROM%%] @%%USERNAME%% tady oxiduje už %%TIME%%.",
    "kickrank": "/me [@%%NAME%%] Nemůžeš vyhodit výše postavenýho borca. To je prostě nemožný tak to pochop...",
    "kick": "/me [@%%NAME%%], @%%USERNAME%% zlobil a tak byl vykopnutej na %%TIME%% minut.",
    "kill": "/me Bot dostal strašnou podpásovku.",
    "rouletteleave": "/me @%%NAME%% si zachránil kůži a odešel z rulety!",
    "songlink": "/me [@%%NAME%%] Link na tu kravinu co hraje je: %%LINK%%",
    "usedlockskip": "/me [%%NAME%% použil/a lockskip.]",
    "lockskippos": "/me [@%%NAME%%] Lockskip nyní posune hráče na pozici %%POSITION%%.",
    "lockguardtime": "/me [@%%NAME%%] Lockguard je nastaven na %%TIME%% minut.",
    "maxlengthtime": "/me [@%%NAME%%] Maximální délka kravin co budeš pouštět nastavena na %%TIME%% minut.",
    "motdset": "/me MotD nastavena na:  %%MSG%%",
    "motdintervalset": "/me MotD interval nastaven na %%INTERVAL%%.",
    "addbotwaitlist": "/me @%%NAME%%, nech mě bejt, dělej že tu nejsem a nelez mi na píseček.",
    "move": "/me [%%NAME%% použil/a move.]",
    "mutednotime": "/me [@%%NAME%%] Zavřel/a hubu @%%USERNAME%%.",
    "mutedmaxtime": "/me [@%%NAME%%] Zavřít někomu hubu můžeš maximálně na %%TIME%% minut.",
    "mutedtime": "/me [@%%NAME%%] Zavřel/a hubu @%%USERNAME%% na dobu %%TIME%% minut.",
    "unmuted": "/me [@%%NAME%%] Zrušil/a ztlumení @%%USERNAME%%.",
    "muterank": "/me [@%%NAME%%] Nemůžeš zavřít hubu někomu, kdo je výše postaven než ty...",
    "oplist": "/me OP list: %%LINK%%",
    "pong": "/me Pong!",
    "reload": "/me Neradujte se bastardi, já jsem hnedkom zpátky.",
    "removenotinwl": "/me [@%%NAME%%] Hráč @%%USERNAME%% není ve frontě.",
    "roomrules": "/me Ksakru, nauč se respektovat pravidla nebo sem nelez... tupče!",
    "sessionstats": "/me [@%%NAME%%] Celkem wootů: %%WOOTS%%, celkem mehů: %%MEHS%%, celkem přidání: %%GRABS%%.",
    "skip": "/me [%%NAME%% Použil/a skip.]",
    "madeby": "/me Tento bot byl vytvořen %%NAME%% a upraven Tessi Tess",
    "activefor": "Svojí přítomností kurvím den už %%TIME%%.",
    "swapinvalid": "/me [@%%NAME%%] Špatnej nick pyčo. Zadej ve formátu !swap @user1 @user2 (nick nesmí obsahovat mezery)",
    "swapwlonly": "/me [@%%NAME%%] Changnout můžeš jenom hovada co si šlapou po hlavách ve frontě!",
    "swapping": "/me Výměna uživatelů %%NAME1%% a %%NAME2%%.",
    "genres": "/me Písničky co byly označeny jako sračky najdeš tu: %%LINK%%",
    "notbanned": "/me [@%%NAME%%] Tenhle zmrd se brání banu.",
    "unmutedeveryone": "/me [@%%NAME%%] vyhlásil zkurvenou amnestii.",
    "unmuteeveryonerank": "/me [@%%NAME%%] Pouze povyšující se manažeři mohou zrušit všem ztlumení.",
    "notmuted": "/me [@%%NAME%%] tomuhle hovadu ještě nikdo nezavřel hubu.",
    "unmuterank": "/me [@%%NAME%%] Nemůžeš zrušit mute někomu kdo má větší ego jak ty.",
    "commandscd": "/me [@%%NAME%%] Nějakej troll nastavil pro šedý krysy omezení na %%TIME%% sekund.",
    "voteratio": "/me [@%%NAME%%] @%%USERNAME%% ~ wootů: %%WOOT%%, mehů: %%MEHS%%, ratio (w/m): %%RATIO%%.",
    "website": "/me Prosím navštivte naše webovky: %%LINK%%",
    "youtube": "/me [%%NAME%%] Link na náš youtube: %%LINK%%",
    "songstatistics": "/me %%ARTIST%% - %%TITLE%%: %%WOOTS%%W/%%GRABS%%G/%%MEHS%%M.",
    "ego": "/me %%NAME%% *EGO UP*",
    "afk": "/me Takže %%NAME%% si dovolil/a jít AFK. -,-"
}
